georouter/__init__.py
georouter/area_creator.py
georouter/clustering.py
georouter/core.py
georouter/data_loader.py
georouter/edge_classifier.py
georouter/elevation.py
georouter/path_finding.c
georouter/path_finding.cpython-39-darwin.so
georouter/routes.py
georouter-0.1.9.dist-info/LICENSE
georouter-0.1.9.dist-info/METADATA
georouter-0.1.9.dist-info/WHEEL
georouter-0.1.9.dist-info/top_level.txt
georouter-0.1.9.dist-info/RECORD
