Metadata-Version: 2.1
Name: georouter
Version: 0.1.9
Summary: Library for generating routes through different preferred environment attributes
Author: David Saldubehere
Project-URL: Homepage, https://github.com/davidsaldubehere/georouter
Classifier: Programming Language :: Python :: 3
Classifier: License :: OSI Approved :: GNU General Public License v3 (GPLv3)
Classifier: Operating System :: OS Independent
Requires-Python: >=3.8
License-File: LICENSE
Requires-Dist: requests
Requires-Dist: numpy
Requires-Dist: pandas
Requires-Dist: scipy
Requires-Dist: scikit-learn
Requires-Dist: scikit-image
Requires-Dist: pyrosm
Requires-Dist: python-igraph
Provides-Extra: dev
Requires-Dist: pytest ; extra == 'dev'
